mlx_llm_server/__init__.py
mlx_llm_server/__main__.py
mlx_llm_server/app.py
mlx_llm_server-0.1.10.dist-info/METADATA
mlx_llm_server-0.1.10.dist-info/WHEEL
mlx_llm_server-0.1.10.dist-info/entry_points.txt
mlx_llm_server-0.1.10.dist-info/top_level.txt
mlx_llm_server-0.1.10.dist-info/RECORD
