Metadata-Version: 2.1
Name: mlx-llm-server
Version: 0.1.10
Summary: server to serve mlx model as an OpenAI compatible API
Home-page: https://github.com/mzbac/mlx-llm
Author: anchen
Author-email: li.anchen.au@gmail.com
License: MIT
Requires-Python: >=3.10
Requires-Dist: mlx-lm >=0.4.0
Requires-Dist: mlx ==0.7.0
Requires-Dist: numpy
Requires-Dist: transformers
